{
  "project_info": {
    "project_number": "191726283967",
    "project_id": "ititask-f8f18",
    "storage_bucket": "ititask-f8f18.firebasestorage.app"
  },
  "client": [
    {
      "client_info": {
        "mobilesdk_app_id": "1:191726283967:android:86a3b8b58c1564a532ea0a",
        "android_client_info": {
          "package_name": "com.example.ititask"
        }
      },
      "oauth_client": [],
      "api_key": [
        {
          "current_key": "AIzaSyC_4UYDXnXMYIxOs4lGOrAeb7gi6r-gKA4"
        }
      ],
      "services": {
        "appinvite_service": {
          "other_platform_oauth_client": []
        }
      }
    }
  ],
  "configuration_version": "1"
}